Semp/Command.py
Semp/Command.pyi
Semp/Progressbar.py
Semp/Progressbar.pyi
Semp/SempWrite.py
Semp/SempWrite.pyi
Semp/__init__.py
Semp/__init__.pyi
Semp/about.py
Semp/test.py
Semp/EasyTkinter/__init__.py
SempCode-2023.6.5.22.5012.dist-info/LISENCE
SempCode-2023.6.5.22.5012.dist-info/METADATA
SempCode-2023.6.5.22.5012.dist-info/README.md
SempCode-2023.6.5.22.5012.dist-info/Semp-0.3.7.2-py3-none-any.whl
SempCode-2023.6.5.22.5012.dist-info/SempCode-0.5.0.3-py3-none-any.whl
SempCode-2023.6.5.22.5012.dist-info/SempCode-0.5.2.13-py3-none-any.whl
SempCode-2023.6.5.22.5012.dist-info/SempCode-0.5.5-py3-none-any.whl
SempCode-2023.6.5.22.5012.dist-info/SempCode-2023.6.5.22.3942-py3-none-any.whl
SempCode-2023.6.5.22.5012.dist-info/SempCode-2023.6.5.22.4886-py3-none-any.whl
SempCode-2023.6.5.22.5012.dist-info/WHEEL
SempCode-2023.6.5.22.5012.dist-info/setup.py
SempCode-2023.6.5.22.5012.dist-info/top_level.txt
SempCode-2023.6.5.22.5012.dist-info/RECORD
