Metadata-Version: 2.1
Name: SempCode
Version: 2023.6.5.22.5012
Summary: Simplified the Python Code
Author: 是真的Win12Home
Author-email: mcdhj-work@outlook.com
License: Mozilla Public License Version 2.0
Classifier: Development Status :: 5 - Production/Stable
License-File: LISENCE
License-File: README.md
License-File: Semp-0.3.7.2-py3-none-any.whl
License-File: SempCode-0.5.0.3-py3-none-any.whl
License-File: SempCode-0.5.2.13-py3-none-any.whl
License-File: SempCode-0.5.5-py3-none-any.whl
License-File: SempCode-2023.6.5.22.3942-py3-none-any.whl
License-File: SempCode-2023.6.5.22.4886-py3-none-any.whl
License-File: setup.py
Requires-Dist: requests
Requires-Dist: pillow
Requires-Dist: pathlib
Requires-Dist: subprocess
Requires-Dist: datetime
Requires-Dist: ctypes
Requires-Dist: ttkthemes
Requires-Dist: random
Requires-Dist: tqdm
Requires-Dist: warnings
